setup.py
git_playback.egg-info/PKG-INFO
git_playback.egg-info/SOURCES.txt
git_playback.egg-info/dependency_links.txt
git_playback.egg-info/entry_points.txt
git_playback.egg-info/requires.txt
git_playback.egg-info/top_level.txt
playback/__init__.py