Metadata-Version: 1.0
Name: git-playback
Version: 0.1.1rc0
Summary: A git command to play back file history.
Home-page: https://github.com/jianli/git-playback
Author: UNKNOWN
Author-email: UNKNOWN
License: UNKNOWN
Platform: UNKNOWN
